brokkr/__init__.py
brokkr/__main__.py
brokkr/constants.py
brokkr/start.py
brokkr/config/__init__.py
brokkr/config/base.py
brokkr/config/confighandlers.py
brokkr/config/log.py
brokkr/config/main.py
brokkr/config/metadata.py
brokkr/config/metadatahandler.py
brokkr/config/mode.py
brokkr/config/modehandler.py
brokkr/config/presets.py
brokkr/config/systempath.py
brokkr/config/systempathhandler.py
brokkr/config/unit.py
brokkr/inputs/__init__.py
brokkr/inputs/adafruitadc.py
brokkr/inputs/adafruiti2c.py
brokkr/inputs/adafruitonewire.py
brokkr/inputs/currenttime.py
brokkr/inputs/gpiocounter.py
brokkr/inputs/modbus.py
brokkr/inputs/network.py
brokkr/inputs/ping.py
brokkr/inputs/runtime.py
brokkr/inputs/smbusi2c.py
brokkr/multiprocess/__init__.py
brokkr/multiprocess/handler.py
brokkr/multiprocess/loglistener.py
brokkr/outputs/__init__.py
brokkr/outputs/binaryfile.py
brokkr/outputs/csvfile.py
brokkr/outputs/print.py
brokkr/pipeline/__init__.py
brokkr/pipeline/base.py
brokkr/pipeline/baseinput.py
brokkr/pipeline/baseoutput.py
brokkr/pipeline/builder.py
brokkr/pipeline/datavalue.py
brokkr/pipeline/decode.py
brokkr/pipeline/multistep.py
brokkr/pipeline/pipeline.py
brokkr/pipeline/queuesteps.py
brokkr/pipeline/utils.py
brokkr/utils/__init__.py
brokkr/utils/cli.py
brokkr/utils/configure.py
brokkr/utils/install.py
brokkr/utils/log.py
brokkr/utils/misc.py
brokkr/utils/network.py
brokkr/utils/output.py
brokkr/utils/ports.py
brokkr/utils/services.py
brokkr-0.4.0.dist-info/LICENSE.txt
brokkr-0.4.0.dist-info/METADATA
brokkr-0.4.0.dist-info/WHEEL
brokkr-0.4.0.dist-info/entry_points.txt
brokkr-0.4.0.dist-info/top_level.txt
brokkr-0.4.0.dist-info/RECORD
