Metadata-Version: 2.1
Name: brokkr
Version: 0.4.0
Summary: A client for data ingest/logging/uplink, remote management and autonomous and central control of scientific IoT sensors as part of the Mjolnir system.
Home-page: https://github.com/project-mjolnir/brokkr
Author: C.A.M. Gerlach/UAH HAMMA group
Author-email: CAM.Gerlach@Gerlach.CAM
License: MIT
Project-URL: Live Demo, https://hamma.dev/
Project-URL: Repository, https://github.com/project-mjolnir/brokkr
Project-URL: Documentation, https://github.com/project-mjolnir/brokkr#readme
Project-URL: Changelog, https://github.com/project-mjolnir/brokkr/blob/master/CHANGELOG.md
Project-URL: Issue Tracker, https://github.com/project-mjolnir/brokkr/issues
Keywords: iot lightning sensor remote control research m2m raspberry pi rpi
Classifier: Development Status :: 4 - Beta
Classifier: Environment :: Console
Classifier: Environment :: No Input/Output (Daemon)
Classifier: Intended Audience :: Science/Research
Classifier: License :: OSI Approved :: MIT License
Classifier: Operating System :: OS Independent
Classifier: Programming Language :: Python :: 3
Classifier: Programming Language :: Python :: 3 :: Only
Classifier: Programming Language :: Python :: 3.6
Classifier: Programming Language :: Python :: 3.7
Classifier: Programming Language :: Python :: 3.8
Classifier: Programming Language :: Python :: 3.9
Classifier: Programming Language :: Python :: 3.10
Classifier: Topic :: Scientific/Engineering :: Atmospheric Science
Classifier: Topic :: Scientific/Engineering :: Physics
Classifier: Topic :: System :: Monitoring
Classifier: Topic :: System :: Networking :: Monitoring :: Hardware Watchdog
Requires-Python: >=3.6
License-File: LICENSE.txt
Requires-Dist: packaging (>=17)
Requires-Dist: simpleeval (>=0.9.11)
Requires-Dist: tomli (>=1.1)
Requires-Dist: tomli-w (>=0.4)
Requires-Dist: serviceinstaller (>=0.2.0) ; sys_platform == "linux"
Provides-Extra: adafruit
Requires-Dist: Adafruit-Blinka ; extra == 'adafruit'
Requires-Dist: adafruit-circuitpython-busdevice ; extra == 'adafruit'
Provides-Extra: all
Requires-Dist: Adafruit-Blinka ; extra == 'all'
Requires-Dist: adafruit-circuitpython-busdevice ; extra == 'all'
Requires-Dist: gpiozero ; extra == 'all'
Requires-Dist: pymodbus ; extra == 'all'
Requires-Dist: pyserial ; extra == 'all'
Requires-Dist: RPi.GPIO ; extra == 'all'
Requires-Dist: smbus2 ; extra == 'all'
Provides-Extra: gpio
Requires-Dist: gpiozero ; extra == 'gpio'
Requires-Dist: RPi.GPIO ; extra == 'gpio'
Provides-Extra: modbus
Requires-Dist: pymodbus ; extra == 'modbus'
Requires-Dist: pyserial ; extra == 'modbus'
Provides-Extra: smbus
Requires-Dist: smbus2 ; extra == 'smbus'
